design.sv
module leading_zero_counter (
    input  [7:0] in,
    output reg [3:0] count
);
    always @(*) begin
        casez (in)
            8'b1???????: count = 4'd0;
            8'b01??????: count = 4'd1;
            8'b001?????: count = 4'd2;
            8'b0001????: count = 4'd3;
            8'b00001???: count = 4'd4;
            8'b000001??: count = 4'd5;
            8'b0000001?: count = 4'd6;
            8'b00000001: count = 4'd7;
            8'b00000000: count = 4'd8;
            default:     count = 4'd0;
        endcase
    end
endmodule

testbench.sv

module tb_lzc;
    reg  [7:0] in;
    wire [3:0] count;

    leading_zero_counter uut (
        .in(in),
        .count(count)
    );

    initial begin
      $dumpfile("leading_zero_counter.vcd");
      $dumpvars;
        $display("Time\tInput\t\tCount");
        $monitor("%0t\t%b\t%d", $time, in, count);

        in = 8'b00000000; #10; // Expect 8
        in = 8'b00000001; #10; // Expect 7
        in = 8'b00000010; #10; // Expect 6
        in = 8'b00000100; #10; // Expect 5
        in = 8'b00001000; #10; // Expect 4
        in = 8'b00010000; #10; // Expect 3
        in = 8'b00100000; #10; // Expect 2
        in = 8'b01000000; #10; // Expect 1
        in = 8'b10000000; #10; // Expect 0
        in = 8'b11111111; #10; // Expect 0
        in = 8'b01111111; #10; // Expect 1
        in = 8'b00111111; #10; // Expect 2
        in = 8'b00000010; #10; // Expect 6

        $finish;
    end
endmodule

leading_zero_counter.vcd
$date
	Wed Jul 30 09:40:04 2025
$end
$version
	Icarus Verilog
$end
$timescale
	1s
$end
$scope module tb_lzc $end
$var wire 4 ! count [3:0] $end
$var reg 8 " in [7:0] $end
$scope module uut $end
$var wire 8 # in [7:0] $end
$var reg 4 $ count [3:0] $end
$upscope $end
$upscope $end
$enddefinitions $end
$comment Show the parameter values. $end
$dumpall
$end
#0
$dumpvars
b1000 $
b0 #
b0 "
b1000 !
$end
#10
b111 !
b111 $
b1 "
b1 #
#20
b110 !
b110 $
b10 "
b10 #
#30
b101 !
b101 $
b100 "
b100 #
#40
b100 !
b100 $
b1000 "
b1000 #
#50
b11 !
b11 $
b10000 "
b10000 #
#60
b10 !
b10 $
b100000 "
b100000 #
#70
b1 !
b1 $
b1000000 "
b1000000 #
#80
b0 !
b0 $
b10000000 "
b10000000 #
#90
b11111111 "
b11111111 #
#100
b1 !
b1 $
b1111111 "
b1111111 #
#110
b10 !
b10 $
b111111 "
b111111 #
#120
b110 !
b110 $
b10 "
b10 #
